{
  "auth": {
    "tododf668a86": {
      "service": "Cognito",
      "providerPlugin": "awscloudformation",
      "dependsOn": [],
      "customAuth": false,
      "frontendAuthConfig": {
        "socialProviders": [],
        "usernameAttributes": [],
        "signupAttributes": [
          "EMAIL"
        ],
        "passwordProtectionSettings": {
          "passwordPolicyMinLength": 8,
          "passwordPolicyCharacters": []
        },
        "mfaConfiguration": "OFF",
        "mfaTypes": [
          "SMS"
        ],
        "verificationMechanisms": [
          "EMAIL"
        ]
      }
    }
  },
  "api": {
    "todo": {
      "service": "AppSync",
      "providerPlugin": "awscloudformation",
      "dependsOn": [
        {
          "category": "auth",
          "resourceName": "tododf668a86",
          "attributes": [
            "UserPoolId"
          ]
        }
      ],
      "output": {
        "authConfig": {
          "defaultAuthentication": {
            "authenticationType": "AMAZON_COGNITO_USER_POOLS",
            "userPoolConfig": {
              "userPoolId": "authtododf668a86"
            }
          },
          "additionalAuthenticationProviders": [
            {
              "authenticationType": "API_KEY",
              "apiKeyConfig": {
                "apiKeyExpirationDays": 365,
                "apiKeyExpirationDate": "2023-05-01T06:21:47.131Z",
                "description": "api description"
              }
            }
          ]
        }
      }
    }
  }
}